.gitignore
LICENSE
README.rst
build.py
setup.py
nfft/__init__.py
nfft/nfft.py
nfft/util.py
nfft_cffi.egg-info/PKG-INFO
nfft_cffi.egg-info/SOURCES.txt
nfft_cffi.egg-info/dependency_links.txt
nfft_cffi.egg-info/top_level.txt
tests/test_nfft.py