Metadata-Version: 1.1
Name: nfft-cffi
Version: 0.2
Summary: Python interface to the NFFT library
Home-page: https://github.com/ghisvail/nfft-cffi
Author: Ghislain Antony Vaillant
Author-email: ghisvail@gmail.com
License: BSD
Keywords: dft nfft
Platform: UNKNOWN
Classifier: Development Status :: 3 - Alpha
Classifier: Intended Audience :: Science/Research
Classifier: License :: OSI Approved :: BSD License
Classifier: Programming Language :: Python
Classifier: Topic :: Software Development
